Workbook

Sheet Model
A1: Agentic B2B Order Intake — Business Case Model
A2: Blue cells = your inputs. Black cells = calculated. Yellow background = key inputs to update before presenting.
A4: A — Current State (Manual)
A5: Orders processed per month | B5: 500 | C5: Total inbound POs handled manually — all channels, all formats.
A6: Average minutes per order (manual intake) | B6: 12 | C6: Default 12 min = midpoint of 8–15 min range. Source: Emporix (2026) documents ~8 min; 2hatslogic (2025) reports 10–15 min. See Sources sheet. Override with your own measurement.
A7: Staff fully-loaded hourly cost (local currency) | B7: 35 | C7: Total hourly cost including salary, benefits, and overhead. Typically 1.25–1.4× base salary ÷ annual hours. Enter your own figure.
A8: Error rate — orders with ≥1 field error (%) | B8: 0.02 | C8: Default 2% = midpoint of 1-3% range. Conexiom (2025): manual orders are 2x more error-prone than automated. Aberdeen (2020): 33% of manually processed POs contain errors. See Sources sheet.
A9: Estimated internal cost per order error (local currency) | B9: 0 | C9: ⚠ No default — enter your own figure. Include: staff rework time, credit note processing, customer communication, and fulfillment delays.
A11: Monthly staff hours on intake | B11: =B5*(B6/60) -> 100 | C11: Orders × (Minutes ÷ 60)
A12: Monthly labour cost (intake) | B12: =B11*B7 -> 3500 | C12: Monthly hours × Hourly cost
A13: Orders with errors per month | B13: =B5*B8 -> 10 | C13: Orders × Error rate
A14: Monthly error cost | B14: =B13*B9 -> 0 | C14: Orders with errors × Cost per error
A15: TOTAL CURRENT MONTHLY COST | B15: =B12+B14 -> 3500 | C15: ="Annual equivalent: $"&TEXT(B15*12,"#,##0") -> Annual equivalent: $42,000
A17: B — Projected State (With Agent)
A18: Expected automation rate — orders auto-submitted (%) | B18: 0.67 | C18: The % of orders the agent resolves end-to-end without human touch. Esker benchmark (Jun 2025, hundreds of CS depts): average 67%, top performers 90%+. Use Sensitivity sheet to model a range. See Sources sheet.
A20: Orders auto-submitted (no human touch) | B20: =B5*B18 -> 335 | C20: Orders × Automation rate
A21: Orders still handled by operator | B21: =B5*(1-B18) -> 165 | C21: Orders × (1 − Automation rate) (Human Review, Clarification, and Reject queues)
A22: Projected monthly labour cost | B22: =B21*(B6/60)*B7 -> 1155 | C22: Human-handled orders × Minutes/60 × Hourly cost. Conservative: assumes full manual time per human-reviewed order.
A23: Projected monthly error cost | B23: =B21*B8*B9 -> 0 | C23: Human-handled orders × Error rate × Cost per error. Auto-submitted orders have no manual re-keying errors.
A24: TOTAL PROJECTED MONTHLY COST | B24: =B22+B23 -> 1155
A26: C — Return on Investment
A27: Estimated implementation cost (local currency) | B27: 0 | C27: Include: infrastructure, integration, testing, and staff training. Does not include the cost of ongoing API usage (Anthropic or equivalent).
A29: Monthly saving | B29: =B15-B24 -> 2345
A30: Annual saving | B30: =B29*12 -> 28140
A31: Payback period (months) | B31: =IF(B27=0,"—",IF(B29<=0,"Does not pay back",TEXT(B27/B29,"0.0"))) -> —
A33: Notes
A34: 1. This model measures direct labour and error-correction costs only. It does not quantify speed-to-revenue gains, scalability benefits, or staff time redirected to higher-value work. Actual returns will be higher.
A35: 2. The model assumes human-reviewed orders require full manual processing time. In practice the agent pre-fills data, reducing operator time.
A36: 3. Replace all yellow-highlighted cells with your organisation's actual data before presenting this output to decision-makers.

Sheet Sensitivity
A1: Sensitivity — Monthly Saving by Automation Rate
A2: Shows monthly saving at different automation rates. All figures pull from your inputs on the Model sheet.
A4: Metric | B4: 50% | C4: 60% | D4: 67% | E4: 75% | F4: 80% | G4: 90%
A5: Orders auto-submitted | B5: =Model!B5*0.5 -> 250 | C5: =Model!B5*0.6 -> 300 | D5: =[1]Model!B5*0.67 -> 335 | E5: =Model!B5*0.75 -> 375 | F5: =Model!B5*0.8 -> 400 | G5: =Model!B5*0.9 -> 450
A6: Orders operator-handled | B6: =Model!B5*(1-0.5) -> 250 | C6: =Model!B5*(1-0.6) -> 200 | D6: =[1]Model!B5*(1-0.67) -> 165 | E6: =Model!B5*(1-0.75) -> 125 | F6: =Model!B5*(1-0.8) -> 100 | G6: =Model!B5*(1-0.9) -> 50
A7: Monthly labour cost | B7: =Model!B5*(1-0.5)*(Model!B6/60)*Model!B7 -> 1750 | C7: =Model!B5*(1-0.6)*(Model!B6/60)*Model!B7 -> 1400 | D7: =[1]Model!B5*(1-0.67)*([1]Model!B6/60)*[1]Model!B7 -> 1155 | E7: =Model!B5*(1-0.75)*(Model!B6/60)*Model!B7 -> 875 | F7: =Model!B5*(1-0.8)*(Model!B6/60)*Model!B7 -> 700 | G7: =Model!B5*(1-0.9)*(Model!B6/60)*Model!B7 -> 350
A8: Monthly error cost | B8: =Model!B5*(1-0.5)*Model!B8*Model!B9 -> 0 | C8: =Model!B5*(1-0.6)*Model!B8*Model!B9 -> 0 | D8: =[1]Model!B5*(1-0.67)*[1]Model!B8*[1]Model!B9 -> 0 | E8: =Model!B5*(1-0.75)*Model!B8*Model!B9 -> 0 | F8: =Model!B5*(1-0.8)*Model!B8*Model!B9 -> 0 | G8: =Model!B5*(1-0.9)*Model!B8*Model!B9 -> 0
A9: Total projected cost | B9: =Model!B5*(1-0.5)*(Model!B6/60)*Model!B7+Model!B5*(1-0.5)*Model!B8*Model!B9 -> 1750 | C9: =Model!B5*(1-0.6)*(Model!B6/60)*Model!B7+Model!B5*(1-0.6)*Model!B8*Model!B9 -> 1400 | D9: =[1]Model!B5*(1-0.67)*([1]Model!B6/60)*[1]Model!B7+[1]Model!B5*(1-0.67)*[1]Model!B8*[1]Model!B9 -> 1155 | E9: =Model!B5*(1-0.75)*(Model!B6/60)*Model!B7+Model!B5*(1-0.75)*Model!B8*Model!B9 -> 875 | F9: =Model!B5*(1-0.8)*(Model!B6/60)*Model!B7+Model!B5*(1-0.8)*Model!B8*Model!B9 -> 700 | G9: =Model!B5*(1-0.9)*(Model!B6/60)*Model!B7+Model!B5*(1-0.9)*Model!B8*Model!B9 -> 350
A10: Monthly saving vs current | B10: =Model!B15-(Model!B5*(1-0.5)*(Model!B6/60)*Model!B7+Model!B5*(1-0.5)*Model!B8*Model!B9) -> 1750 | C10: =Model!B15-(Model!B5*(1-0.6)*(Model!B6/60)*Model!B7+Model!B5*(1-0.6)*Model!B8*Model!B9) -> 2100 | D10: =[1]Model!B15-([1]Model!B5*(1-0.67)*([1]Model!B6/60)*[1]Model!B7+[1]Model!B5*(1-0.67)*[1]Model!B8*[1]Model!B9) -> 2345 | E10: =Model!B15-(Model!B5*(1-0.75)*(Model!B6/60)*Model!B7+Model!B5*(1-0.75)*Model!B8*Model!B9) -> 2625 | F10: =Model!B15-(Model!B5*(1-0.8)*(Model!B6/60)*Model!B7+Model!B5*(1-0.8)*Model!B8*Model!B9) -> 2800 | G10: =Model!B15-(Model!B5*(1-0.9)*(Model!B6/60)*Model!B7+Model!B5*(1-0.9)*Model!B8*Model!B9) -> 3150
A11: Annual saving | B11: =(Model!B15-(Model!B5*(1-0.5)*(Model!B6/60)*Model!B7+Model!B5*(1-0.5)*Model!B8*Model!B9))*12 -> 21000 | C11: =(Model!B15-(Model!B5*(1-0.6)*(Model!B6/60)*Model!B7+Model!B5*(1-0.6)*Model!B8*Model!B9))*12 -> 25200 | D11: =([1]Model!B15-([1]Model!B5*(1-0.67)*([1]Model!B6/60)*[1]Model!B7+[1]Model!B5*(1-0.67)*[1]Model!B8*[1]Model!B9))*12 -> 28140 | E11: =(Model!B15-(Model!B5*(1-0.75)*(Model!B6/60)*Model!B7+Model!B5*(1-0.75)*Model!B8*Model!B9))*12 -> 31500 | F11: =(Model!B15-(Model!B5*(1-0.8)*(Model!B6/60)*Model!B7+Model!B5*(1-0.8)*Model!B8*Model!B9))*12 -> 33600 | G11: =(Model!B15-(Model!B5*(1-0.9)*(Model!B6/60)*Model!B7+Model!B5*(1-0.9)*Model!B8*Model!B9))*12 -> 37800
A12: Payback (months) | B12: =IF(Model!B27=0,"—",IF(Model!B15-(Model!B5*(1-0.5)*(Model!B6/60)*Model!B7+Model!B5*(1-0.5)*Model!B8*Model!B9)<=0,"N/A",TEXT(Model!B27/(Model!B15-(Model!B5*(1-0.5)*(Model!B6/60)*Model!B7+Model!B5*(1-0.5)*Model!B8*Model!B9)),"0.0"))) -> — | C12: =IF(Model!B27=0,"—",IF(Model!B15-(Model!B5*(1-0.6)*(Model!B6/60)*Model!B7+Model!B5*(1-0.6)*Model!B8*Model!B9)<=0,"N/A",TEXT(Model!B27/(Model!B15-(Model!B5*(1-0.6)*(Model!B6/60)*Model!B7+Model!B5*(1-0.6)*Model!B8*Model!B9)),"0.0"))) -> — | D12: =IF([1]Model!B27=0,"—",IF([1]Model!B15-([1]Model!B5*(1-0.67)*([1]Model!B6/60)*[1]Model!B7+[1]Model!B5*(1-0.67)*[1]Model!B8*[1]Model!B9)<=0,"N/A",TEXT([1]Model!B27/([1]Model!B15-([1]Model!B5*(1-0.67)*([1]Model!B6/60)*[1]Model!B7+[1]Model!B5*(1-0.67)*[1]Model!B8*[1]Model!B9)),"0.0"))) -> — | E12: =IF(Model!B27=0,"—",IF(Model!B15-(Model!B5*(1-0.75)*(Model!B6/60)*Model!B7+Model!B5*(1-0.75)*Model!B8*Model!B9)<=0,"N/A",TEXT(Model!B27/(Model!B15-(Model!B5*(1-0.75)*(Model!B6/60)*Model!B7+Model!B5*(1-0.75)*Model!B8*Model!B9)),"0.0"))) -> — | F12: =IF(Model!B27=0,"—",IF(Model!B15-(Model!B5*(1-0.8)*(Model!B6/60)*Model!B7+Model!B5*(1-0.8)*Model!B8*Model!B9)<=0,"N/A",TEXT(Model!B27/(Model!B15-(Model!B5*(1-0.8)*(Model!B6/60)*Model!B7+Model!B5*(1-0.8)*Model!B8*Model!B9)),"0.0"))) -> — | G12: =IF(Model!B27=0,"—",IF(Model!B15-(Model!B5*(1-0.9)*(Model!B6/60)*Model!B7+Model!B5*(1-0.9)*Model!B8*Model!B9)<=0,"N/A",TEXT(Model!B27/(Model!B15-(Model!B5*(1-0.9)*(Model!B6/60)*Model!B7+Model!B5*(1-0.9)*Model!B8*Model!B9)),"0.0"))) -> —
A14: Base case (70%) highlighted in blue. Change B18 on Model sheet to adjust.

Sheet Sources
A1: Sources & Methodology
A3: Data point | B3: Figure used | C3: Source | D3: Date | E3: URL
A4: Minutes per order (manual intake) — lower bound | B4: ~8 minutes | C4: Emporix — "B2B Order Processing Automation: How AI Cuts Handling Time by 87%" | D4: 2026 | E4: https://www.emporix.com/blog/b2b-order-processing-automation-ai
A5: Minutes per order (manual intake) — upper range | B5: 10–15 minutes | C5: 2hatslogic — "Why Small B2B Companies Should Automate Order Capture Now" | D5: Dec 2025 | E5: https://www.2hatslogic.com/blog/why-smbs-should-automate-order-capture/
A6: Cost per order (B2B intake) | B6: €25–€100 | C6: Emporix — "B2B Order Processing Automation: How AI Cuts Handling Time by 87%" | D6: 2026 | E6: https://www.emporix.com/blog/b2b-order-processing-automation-ai
A7: Manual order entry error rate | B7: 1%–3% per order | C7: Conexiom — "The Real Cost of Manual Order Entry in B2B Operations" (citing APQC data entry benchmarks) | D7: Jul 2025 | E7: https://conexiom.com/blog/the-real-cost-of-manual-order-entry-in-b2b-operations
A8: Field-level error compounding | B8: ~24% of orders have ≥1 error at 3%/field | C8: Nventory — "Hidden Costs of Manual Order Processing" | D8: Oct 2025 | E8: https://nventory.io/blog/manual-order-processing-costs
A9: Automation time reduction (intake) | B9: ~87% (8 min → <60 sec) | C9: Emporix — documented ACR deployment case study | D9: 2026 | E9: https://www.emporix.com/blog/b2b-order-processing-automation-ai
A12: Methodology: The model uses cited figures as default inputs only. All inputs should be replaced with organisation-specific data before presenting results. The automation rate is not cited from any source — it is the key scenario variable the adopter controls.
A13: Average touchless order rate — industry benchmark | B13: 67% average; 90%+ for top performers | C13: Esker — "How Order Management Benchmarks Can Guide Smarter Business Decisions" (Jun 2025 webinar, hundreds of CS depts) | D13: Oct 2025 | E13: https://www.esker.com/blog/customer-service/how-order-management-benchmarks-can-guide-smarter-business-decisions/
A14: Error rate reduction after automation deployment | B14: 5% → 0.3% (documented case) | C14: Esker — same benchmark article, single-customer case study | D14: Oct 2025 | E14: https://www.esker.com/blog/customer-service/how-order-management-benchmarks-can-guide-smarter-business-decisions/
A15: Manual vs automated orders — shipping and accuracy | B15: 33% more likely to ship late; 2x more error-prone | C15: Conexiom — homepage "Order Automation Intelligence for Manufacturers & Distributors" | D15: 2025 | E15: https://conexiom.com/homepage-c
A16: CSR time spent on manual order entry | B16: Up to 80% of working day | C16: Conexiom — product description, Order Automation platform | D16: 2025 | E16: https://conexiom.com/homepage-c
A17: Manual PO cost per document (directional, 2020 data) | B17: $43 per PO | C17: Aberdeen Group, 165 organizations, via IBM Sterling B2B blog — "New Research Helps Build the Case for Small Partner Automation" | D17: Jan 2020 | E17: https://community.ibm.com/community/user/blogs/brian-bailey/2020/01/22/new-research-helps-build-the-case-for-small-partne
A18: Manual PO document-level error rate (directional, 2020 data) | B18: 33% of manually processed POs have errors | C18: Aberdeen Group, 165 organizations, via IBM Sterling B2B blog | D18: Jan 2020 | E18: https://community.ibm.com/community/user/blogs/brian-bailey/2020/01/22/new-research-helps-build-the-case-for-small-partne
A19: Cost to fix a manual PO error (directional, 2020 data) | B19: $182 per error correction | C19: Aberdeen Group, 165 organizations, via IBM Sterling B2B blog | D19: Jan 2020 | E19: https://community.ibm.com/community/user/blogs/brian-bailey/2020/01/22/new-research-helps-build-the-case-for-small-partne
